aind_metadata_upgrader/__init__.py
aind_metadata_upgrader/base.py
aind_metadata_upgrader/settings.py
aind_metadata_upgrader/sync.py
aind_metadata_upgrader/upgrade.py
aind_metadata_upgrader/upgrade_mapping.py
aind_metadata_upgrader/acquisition/__init__.py
aind_metadata_upgrader/acquisition/v1v2.py
aind_metadata_upgrader/acquisition/v1v2_tiles.py
aind_metadata_upgrader/data_description/__init__.py
aind_metadata_upgrader/data_description/v1v2.py
aind_metadata_upgrader/instrument/__init__.py
aind_metadata_upgrader/instrument/v1v2.py
aind_metadata_upgrader/instrument/v1v2_devices.py
aind_metadata_upgrader/metadata/__init__.py
aind_metadata_upgrader/metadata/v1v2.py
aind_metadata_upgrader/procedures/__init__.py
aind_metadata_upgrader/procedures/v1v2.py
aind_metadata_upgrader/procedures/v1v2_injections.py
aind_metadata_upgrader/procedures/v1v2_procedures.py
aind_metadata_upgrader/processing/__init__.py
aind_metadata_upgrader/processing/v1v2.py
aind_metadata_upgrader/quality_control/__init__.py
aind_metadata_upgrader/quality_control/v1v2.py
aind_metadata_upgrader/rig/__init__.py
aind_metadata_upgrader/rig/v1v2.py
aind_metadata_upgrader/rig/v1v2_devices.py
aind_metadata_upgrader/session/__init__.py
aind_metadata_upgrader/session/v1v2.py
aind_metadata_upgrader/subject/__init__.py
aind_metadata_upgrader/subject/v1v2.py
aind_metadata_upgrader/utils/__init__.py
aind_metadata_upgrader/utils/v1v2_metadata_utils.py
aind_metadata_upgrader/utils/v1v2_utils.py
aind_metadata_upgrader/utils/validators.py
aind_metadata_upgrader-0.6.1.dist-info/licenses/LICENSE
aind_metadata_upgrader-0.6.1.dist-info/METADATA
aind_metadata_upgrader-0.6.1.dist-info/WHEEL
aind_metadata_upgrader-0.6.1.dist-info/top_level.txt
aind_metadata_upgrader-0.6.1.dist-info/RECORD
