Metadata-Version: 2.4
Name: aind-metadata-upgrader
Version: 0.6.1
Summary: Generated from aind-library-template
Author: Allen Institute for Neural Dynamics
License: MIT
Classifier: Programming Language :: Python :: 3
Requires-Python: >=3.10
License-File: LICENSE
Requires-Dist: aind-data-schema<3,>=2.4.0
Requires-Dist: packaging
Requires-Dist: aind-data-access-api[docdb]
Provides-Extra: dev
Requires-Dist: black; extra == "dev"
Requires-Dist: coverage; extra == "dev"
Requires-Dist: flake8; extra == "dev"
Requires-Dist: interrogate; extra == "dev"
Requires-Dist: isort; extra == "dev"
Requires-Dist: Sphinx; extra == "dev"
Requires-Dist: tzlocal; extra == "dev"
Requires-Dist: furo; extra == "dev"
Requires-Dist: aind-metadata-upgrader[sync]; extra == "dev"
Provides-Extra: sync
Requires-Dist: aind-data-access-api[rds]; extra == "sync"
Dynamic: license-file
